texttoimage/__init__.py
texttoimage-0.0.2.dist-info/LICENSE
texttoimage-0.0.2.dist-info/METADATA
texttoimage-0.0.2.dist-info/WHEEL
texttoimage-0.0.2.dist-info/top_level.txt
texttoimage-0.0.2.dist-info/RECORD
