Metadata-Version: 2.1
Name: texttoimage
Version: 0.0.2
Summary: Texttoimage is a Python library for converting text to a transparent image.
Home-page: https://github.com/zhiwehu/texttoimage
Author: Jeffrey Hu
Author-email: zhiwehu@gmail.com
License: UNKNOWN
Platform: UNKNOWN
Classifier: Programming Language :: Python :: 3
Classifier: License :: OSI Approved :: MIT License
Classifier: Operating System :: OS Independent
Requires-Python: >=3.6
